fluxoperator/__init__.py
fluxoperator/api_client.py
fluxoperator/client.py
fluxoperator/configuration.py
fluxoperator/decorator.py
fluxoperator/defaults.py
fluxoperator/exceptions.py
fluxoperator/rest.py
fluxoperator/api/__init__.py
fluxoperator/models/__init__.py
fluxoperator/models/bursted_cluster.py
fluxoperator/models/bursting.py
fluxoperator/models/commands.py
fluxoperator/models/container_resources.py
fluxoperator/models/container_volume.py
fluxoperator/models/flux_broker.py
fluxoperator/models/flux_container.py
fluxoperator/models/flux_restful.py
fluxoperator/models/flux_scheduler.py
fluxoperator/models/flux_spec.py
fluxoperator/models/flux_user.py
fluxoperator/models/life_cycle.py
fluxoperator/models/logging_spec.py
fluxoperator/models/mini_cluster.py
fluxoperator/models/mini_cluster_archive.py
fluxoperator/models/mini_cluster_container.py
fluxoperator/models/mini_cluster_existing_volume.py
fluxoperator/models/mini_cluster_list.py
fluxoperator/models/mini_cluster_spec.py
fluxoperator/models/mini_cluster_status.py
fluxoperator/models/mini_cluster_user.py
fluxoperator/models/mini_cluster_volume.py
fluxoperator/models/network.py
fluxoperator/models/pod_spec.py
fluxoperator/models/secret.py
fluxoperator/models/security_context.py
fluxoperator/resource/__init__.py
fluxoperator/resource/network.py
fluxoperator/resource/pods.py
test/__init__.py
test/test_bursted_cluster.py
test/test_bursting.py
test/test_commands.py
test/test_container_resources.py
test/test_container_volume.py
test/test_flux_broker.py
test/test_flux_container.py
test/test_flux_restful.py
test/test_flux_scheduler.py
test/test_flux_spec.py
test/test_flux_user.py
test/test_life_cycle.py
test/test_logging_spec.py
test/test_mini_cluster.py
test/test_mini_cluster_archive.py
test/test_mini_cluster_container.py
test/test_mini_cluster_list.py
test/test_mini_cluster_spec.py
test/test_mini_cluster_status.py
test/test_mini_cluster_user.py
test/test_network.py
test/test_pod_spec.py
test/test_secret.py
fluxoperator-0.2.0.dist-info/METADATA
fluxoperator-0.2.0.dist-info/WHEEL
fluxoperator-0.2.0.dist-info/top_level.txt
fluxoperator-0.2.0.dist-info/RECORD
