Metadata-Version: 2.1
Name: fluxoperator
Version: 0.2.0
Summary: Python SDK for the Flux Operator
Home-page: https://github.com/flux-framework/flux-operator/tree/main/python-sdk/v1alpha2
Author: Vanessasaurus
Author-email: vsoch@users.noreply.github.com
Maintainer: Vanessasaurus
License: Apache 2.0
Keywords: flux-operator,flux-framework,kubernetes,workflows,jobs-api
Classifier: Intended Audience :: Science/Research
Classifier: Intended Audience :: Developers
Classifier: License :: OSI Approved :: Apache Software License
Classifier: Programming Language :: C
Classifier: Programming Language :: Python
Classifier: Topic :: Software Development
Classifier: Topic :: Scientific/Engineering
Classifier: Operating System :: Unix
Classifier: Programming Language :: Python :: 3.7
Requires-Dist: kubernetes
Requires-Dist: requests
